{"windows":[{"x":229,"y":43,"visible":false,"name":"SamplerEditor"},{"x":0,"y":96,"visible":true,"name":"LayerEditor"},{"x":0,"y":1,"visible":false,"name":"WorldEditor"},{"x":1064,"y":167,"visible":true,"name":"SamplerOverview"},{"x":0,"y":0,"visible":false,"name":"ProjectWindow"},{"x":0,"y":0,"visible":false,"name":"ColorInterpreterList"},{"x":0,"y":0,"visible":false,"name":"SettingsWindow"},{"x":0,"y":0,"visible":false,"name":"AboutWindow"}],"screenWidth":1440,"screenHeight":807,"autoRefresh":false,"showExitDialog":true}